local_zebra_printer/__init__.py
local_zebra_printer/local_zebra_printer.py
local_zebra_printer/run_zebra_printer_script.py
local_zebra_printer/socket_listener.py
local_zebra_printer/zpl_methods.py
local_zebra_printer-0.0.3.dist-info/LICENSE
local_zebra_printer-0.0.3.dist-info/METADATA
local_zebra_printer-0.0.3.dist-info/WHEEL
local_zebra_printer-0.0.3.dist-info/entry_points.txt
local_zebra_printer-0.0.3.dist-info/top_level.txt
local_zebra_printer-0.0.3.dist-info/RECORD
