Metadata-Version: 2.2
Name: local_zebra_printer
Version: 0.0.3
Summary: Run a virtual zpl printer.
Author-email: Example Author <Lucas.Denissen@gmail.com>
Project-URL: Homepage, https://github.com/pypa/sampleproject
Project-URL: Bug Tracker, https://github.com/pypa/sampleproject/issues
Classifier: Programming Language :: Python :: 3
Classifier: License :: OSI Approved :: MIT License
Classifier: Operating System :: OS Independent
Requires-Python: >=3.7
License-File: LICENSE
Requires-Dist: requests>=2.0.0
Requires-Dist: pillow>=9.0.0
